{
  "ControlStates": {
    "background_2": {
      "AllowAccessToGlobals": true,
      "ControlPropertyState": [
        {
          "AFDDataSourceName": "",
          "AutoRuleBindingEnabled": false,
          "AutoRuleBindingString": "",
          "InvariantPropertyName": "Fill",
          "IsLockable": false,
          "NameMapSourceSchema": "?"
        },
        {
          "AFDDataSourceName": "",
          "AutoRuleBindingEnabled": false,
          "AutoRuleBindingString": "600",
          "InvariantPropertyName": "Height",
          "IsLockable": false,
          "NameMapSourceSchema": "?"
        },
        {
          "AFDDataSourceName": "",
          "AutoRuleBindingEnabled": false,
          "AutoRuleBindingString": "",
          "InvariantPropertyName": "Width",
          "IsLockable": false,
          "NameMapSourceSchema": "?"
        },
        "X",
        "Y",
        "ZIndex",
        "BorderRadius",
        {
          "AFDDataSourceName": "",
          "AutoRuleBindingEnabled": false,
          "AutoRuleBindingString": "true",
          "InvariantPropertyName": "DarkMode",
          "IsLockable": false,
          "NameMapSourceSchema": "?"
        }
      ],
      "HasDynamicProperties": false,
      "IsAutoGenerated": false,
      "IsComponentDefinition": false,
      "IsDataControl": false,
      "IsFromScreenLayout": false,
      "IsGroupControl": false,
      "IsLocked": false,
      "LayoutName": "",
      "Metadata": {
        "AllowAccessToGlobals": false,
        "AllowCustomization": true,
        "Description": "カード等"
      },
      "MetaDataIDKey": "",
      "Name": "background_2",
      "ParentIndex": 0,
      "PersistMetaDataIDKey": false,
      "Properties": [
        {
          "Category": "Data",
          "PropertyName": "BorderRadius",
          "RuleProviderType": "System"
        },
        {
          "Category": "Data",
          "PropertyName": "DarkMode",
          "RuleProviderType": "Unknown"
        },
        {
          "Category": "Design",
          "PropertyName": "Fill",
          "RuleProviderType": "System"
        },
        {
          "Category": "Design",
          "PropertyName": "Height",
          "RuleProviderType": "Unknown"
        },
        {
          "Category": "Design",
          "PropertyName": "Width",
          "RuleProviderType": "Unknown"
        },
        {
          "Category": "Design",
          "PropertyName": "X",
          "RuleProviderType": "Unknown"
        },
        {
          "Category": "Design",
          "PropertyName": "Y",
          "RuleProviderType": "Unknown"
        },
        {
          "Category": "Design",
          "PropertyName": "ZIndex",
          "RuleProviderType": "Unknown"
        }
      ],
      "StyleName": "",
      "Type": "ControlInfo"
    },
    "Button_2": {
      "AllowAccessToGlobals": true,
      "ControlPropertyState": [
        {
          "AFDDataSourceName": "",
          "AutoRuleBindingEnabled": false,
          "AutoRuleBindingString": "",
          "InvariantPropertyName": "Fill",
          "IsLockable": false,
          "NameMapSourceSchema": "?"
        },
        "Height",
        "Width",
        "X",
        "Y",
        "ZIndex",
        {
          "AFDDataSourceName": "",
          "AutoRuleBindingEnabled": false,
          "AutoRuleBindingString": "\"Text\"",
          "InvariantPropertyName": "OnSelect",
          "IsLockable": false,
          "NameMapSourceSchema": "?"
        },
        "ButtonSelected",
        {
          "AFDDataSourceName": "",
          "AutoRuleBindingEnabled": false,
          "AutoRuleBindingString": "",
          "InvariantPropertyName": "IconName",
          "IsLockable": false,
          "NameMapSourceSchema": "?"
        },
        "IconColorActive",
        {
          "AFDDataSourceName": "",
          "AutoRuleBindingEnabled": false,
          "AutoRuleBindingString": "\"#454545\"",
          "InvariantPropertyName": "IconColour",
          "IsLockable": false,
          "NameMapSourceSchema": "?"
        },
        {
          "AFDDataSourceName": "",
          "AutoRuleBindingEnabled": false,
          "AutoRuleBindingString": "false",
          "InvariantPropertyName": "LinealGradient",
          "IsLockable": false,
          "NameMapSourceSchema": "?"
        },
        {
          "AFDDataSourceName": "",
          "AutoRuleBindingEnabled": false,
          "AutoRuleBindingString": "\"#2c3e50\"",
          "InvariantPropertyName": "LinealGradientColor1",
          "IsLockable": false,
          "NameMapSourceSchema": "?"
        },
        {
          "AFDDataSourceName": "",
          "AutoRuleBindingEnabled": false,
          "AutoRuleBindingString": "\"#3498db\"",
          "InvariantPropertyName": "LinealGradientColor2",
          "IsLockable": false,
          "NameMapSourceSchema": "?"
        },
        "BorderRadius",
        "icontext",
        "TextInput",
        "Fontsizes",
        {
          "AFDDataSourceName": "",
          "AutoRuleBindingEnabled": false,
          "AutoRuleBindingString": "true",
          "InvariantPropertyName": "DarkMode",
          "IsLockable": false,
          "NameMapSourceSchema": "?"
        }
      ],
      "HasDynamicProperties": false,
      "IsAutoGenerated": false,
      "IsComponentDefinition": false,
      "IsDataControl": false,
      "IsFromScreenLayout": false,
      "IsGroupControl": false,
      "IsLocked": false,
      "LayoutName": "",
      "Metadata": {
        "AllowAccessToGlobals": false,
        "AllowCustomization": true,
        "Description": "ボタン"
      },
      "MetaDataIDKey": "",
      "Name": "Button_2",
      "ParentIndex": 4,
      "PersistMetaDataIDKey": false,
      "Properties": [
        {
          "Category": "Data",
          "PropertyName": "IconName",
          "RuleProviderType": "Unknown"
        },
        {
          "Category": "Data",
          "PropertyName": "LinealGradientColor2",
          "RuleProviderType": "Unknown"
        },
        {
          "Category": "Data",
          "PropertyName": "LinealGradientColor1",
          "RuleProviderType": "Unknown"
        },
        {
          "Category": "Data",
          "PropertyName": "LinealGradient",
          "RuleProviderType": "System"
        },
        {
          "Category": "Data",
          "PropertyName": "IconColour",
          "RuleProviderType": "System"
        },
        {
          "Category": "Data",
          "PropertyName": "IconColorActive",
          "RuleProviderType": "System"
        },
        {
          "Category": "Data",
          "PropertyName": "BorderRadius",
          "RuleProviderType": "System"
        },
        {
          "Category": "Data",
          "PropertyName": "ButtonSelected",
          "RuleProviderType": "System"
        },
        {
          "Category": "Data",
          "PropertyName": "icontext",
          "RuleProviderType": "System"
        },
        {
          "Category": "Data",
          "PropertyName": "TextInput",
          "RuleProviderType": "System"
        },
        {
          "Category": "Data",
          "PropertyName": "Fontsizes",
          "RuleProviderType": "System"
        },
        {
          "Category": "Data",
          "PropertyName": "DarkMode",
          "RuleProviderType": "Unknown"
        },
        {
          "Category": "Design",
          "PropertyName": "Height",
          "RuleProviderType": "Unknown"
        },
        {
          "Category": "Design",
          "PropertyName": "Width",
          "RuleProviderType": "Unknown"
        },
        {
          "Category": "Design",
          "PropertyName": "X",
          "RuleProviderType": "Unknown"
        },
        {
          "Category": "Design",
          "PropertyName": "Y",
          "RuleProviderType": "Unknown"
        },
        {
          "Category": "Design",
          "PropertyName": "ZIndex",
          "RuleProviderType": "Unknown"
        },
        {
          "Category": "Design",
          "PropertyName": "Fill",
          "RuleProviderType": "System"
        },
        {
          "Category": "Behavior",
          "PropertyName": "OnSelect",
          "RuleProviderType": "Unknown"
        }
      ],
      "StyleName": "",
      "Type": "ControlInfo"
    },
    "Button_5": {
      "AllowAccessToGlobals": true,
      "ControlPropertyState": [
        {
          "AFDDataSourceName": "",
          "AutoRuleBindingEnabled": false,
          "AutoRuleBindingString": "",
          "InvariantPropertyName": "Fill",
          "IsLockable": false,
          "NameMapSourceSchema": "?"
        },
        "Height",
        "Width",
        "X",
        "Y",
        "ZIndex",
        {
          "AFDDataSourceName": "",
          "AutoRuleBindingEnabled": false,
          "AutoRuleBindingString": "\"Text\"",
          "InvariantPropertyName": "OnSelect",
          "IsLockable": false,
          "NameMapSourceSchema": "?"
        },
        "ButtonSelected",
        {
          "AFDDataSourceName": "",
          "AutoRuleBindingEnabled": false,
          "AutoRuleBindingString": "",
          "InvariantPropertyName": "IconName",
          "IsLockable": false,
          "NameMapSourceSchema": "?"
        },
        "IconColorActive",
        {
          "AFDDataSourceName": "",
          "AutoRuleBindingEnabled": false,
          "AutoRuleBindingString": "\"#454545\"",
          "InvariantPropertyName": "IconColour",
          "IsLockable": false,
          "NameMapSourceSchema": "?"
        },
        {
          "AFDDataSourceName": "",
          "AutoRuleBindingEnabled": false,
          "AutoRuleBindingString": "false",
          "InvariantPropertyName": "LinealGradient",
          "IsLockable": false,
          "NameMapSourceSchema": "?"
        },
        {
          "AFDDataSourceName": "",
          "AutoRuleBindingEnabled": false,
          "AutoRuleBindingString": "\"#2c3e50\"",
          "InvariantPropertyName": "LinealGradientColor1",
          "IsLockable": false,
          "NameMapSourceSchema": "?"
        },
        {
          "AFDDataSourceName": "",
          "AutoRuleBindingEnabled": false,
          "AutoRuleBindingString": "\"#3498db\"",
          "InvariantPropertyName": "LinealGradientColor2",
          "IsLockable": false,
          "NameMapSourceSchema": "?"
        },
        "BorderRadius",
        {
          "AFDDataSourceName": "",
          "AutoRuleBindingEnabled": false,
          "AutoRuleBindingString": "",
          "InvariantPropertyName": "icontext",
          "IsLockable": false,
          "NameMapSourceSchema": "?"
        },
        {
          "AFDDataSourceName": "",
          "AutoRuleBindingEnabled": false,
          "AutoRuleBindingString": "",
          "InvariantPropertyName": "TextInput",
          "IsLockable": false,
          "NameMapSourceSchema": "?"
        },
        {
          "AFDDataSourceName": "",
          "AutoRuleBindingEnabled": false,
          "AutoRuleBindingString": "",
          "InvariantPropertyName": "Fontsizes",
          "IsLockable": false,
          "NameMapSourceSchema": "?"
        },
        {
          "AFDDataSourceName": "",
          "AutoRuleBindingEnabled": false,
          "AutoRuleBindingString": "true",
          "InvariantPropertyName": "DarkMode",
          "IsLockable": false,
          "NameMapSourceSchema": "?"
        }
      ],
      "HasDynamicProperties": false,
      "IsAutoGenerated": false,
      "IsComponentDefinition": false,
      "IsDataControl": false,
      "IsFromScreenLayout": false,
      "IsGroupControl": false,
      "IsLocked": false,
      "LayoutName": "",
      "Metadata": {
        "AllowAccessToGlobals": false,
        "AllowCustomization": true,
        "Description": "ボタン"
      },
      "MetaDataIDKey": "",
      "Name": "Button_5",
      "ParentIndex": 4,
      "PersistMetaDataIDKey": false,
      "Properties": [
        {
          "Category": "Data",
          "PropertyName": "IconName",
          "RuleProviderType": "Unknown"
        },
        {
          "Category": "Data",
          "PropertyName": "LinealGradientColor2",
          "RuleProviderType": "Unknown"
        },
        {
          "Category": "Data",
          "PropertyName": "LinealGradientColor1",
          "RuleProviderType": "Unknown"
        },
        {
          "Category": "Data",
          "PropertyName": "LinealGradient",
          "RuleProviderType": "System"
        },
        {
          "Category": "Data",
          "PropertyName": "IconColour",
          "RuleProviderType": "System"
        },
        {
          "Category": "Data",
          "PropertyName": "IconColorActive",
          "RuleProviderType": "System"
        },
        {
          "Category": "Data",
          "PropertyName": "BorderRadius",
          "RuleProviderType": "System"
        },
        {
          "Category": "Data",
          "PropertyName": "ButtonSelected",
          "RuleProviderType": "System"
        },
        {
          "Category": "Data",
          "PropertyName": "icontext",
          "RuleProviderType": "Unknown"
        },
        {
          "Category": "Data",
          "PropertyName": "TextInput",
          "RuleProviderType": "Unknown"
        },
        {
          "Category": "Data",
          "PropertyName": "Fontsizes",
          "RuleProviderType": "Unknown"
        },
        {
          "Category": "Data",
          "PropertyName": "DarkMode",
          "RuleProviderType": "Unknown"
        },
        {
          "Category": "Design",
          "PropertyName": "Height",
          "RuleProviderType": "Unknown"
        },
        {
          "Category": "Design",
          "PropertyName": "Width",
          "RuleProviderType": "Unknown"
        },
        {
          "Category": "Design",
          "PropertyName": "X",
          "RuleProviderType": "Unknown"
        },
        {
          "Category": "Design",
          "PropertyName": "Y",
          "RuleProviderType": "Unknown"
        },
        {
          "Category": "Design",
          "PropertyName": "ZIndex",
          "RuleProviderType": "Unknown"
        },
        {
          "Category": "Design",
          "PropertyName": "Fill",
          "RuleProviderType": "System"
        },
        {
          "Category": "Behavior",
          "PropertyName": "OnSelect",
          "RuleProviderType": "Unknown"
        }
      ],
      "StyleName": "",
      "Type": "ControlInfo"
    },
    "Button_6": {
      "AllowAccessToGlobals": true,
      "ControlPropertyState": [
        {
          "AFDDataSourceName": "",
          "AutoRuleBindingEnabled": false,
          "AutoRuleBindingString": "",
          "InvariantPropertyName": "Fill",
          "IsLockable": false,
          "NameMapSourceSchema": "?"
        },
        "Height",
        "Width",
        "X",
        "Y",
        "ZIndex",
        {
          "AFDDataSourceName": "",
          "AutoRuleBindingEnabled": false,
          "AutoRuleBindingString": "\"Text\"",
          "InvariantPropertyName": "OnSelect",
          "IsLockable": false,
          "NameMapSourceSchema": "?"
        },
        "ButtonSelected",
        {
          "AFDDataSourceName": "",
          "AutoRuleBindingEnabled": false,
          "AutoRuleBindingString": "",
          "InvariantPropertyName": "IconName",
          "IsLockable": false,
          "NameMapSourceSchema": "?"
        },
        "IconColorActive",
        {
          "AFDDataSourceName": "",
          "AutoRuleBindingEnabled": false,
          "AutoRuleBindingString": "\"#454545\"",
          "InvariantPropertyName": "IconColour",
          "IsLockable": false,
          "NameMapSourceSchema": "?"
        },
        {
          "AFDDataSourceName": "",
          "AutoRuleBindingEnabled": false,
          "AutoRuleBindingString": "false",
          "InvariantPropertyName": "LinealGradient",
          "IsLockable": false,
          "NameMapSourceSchema": "?"
        },
        {
          "AFDDataSourceName": "",
          "AutoRuleBindingEnabled": false,
          "AutoRuleBindingString": "\"#2c3e50\"",
          "InvariantPropertyName": "LinealGradientColor1",
          "IsLockable": false,
          "NameMapSourceSchema": "?"
        },
        {
          "AFDDataSourceName": "",
          "AutoRuleBindingEnabled": false,
          "AutoRuleBindingString": "\"#3498db\"",
          "InvariantPropertyName": "LinealGradientColor2",
          "IsLockable": false,
          "NameMapSourceSchema": "?"
        },
        "BorderRadius",
        {
          "AFDDataSourceName": "",
          "AutoRuleBindingEnabled": false,
          "AutoRuleBindingString": "",
          "InvariantPropertyName": "icontext",
          "IsLockable": false,
          "NameMapSourceSchema": "?"
        },
        {
          "AFDDataSourceName": "",
          "AutoRuleBindingEnabled": false,
          "AutoRuleBindingString": "",
          "InvariantPropertyName": "TextInput",
          "IsLockable": false,
          "NameMapSourceSchema": "?"
        },
        {
          "AFDDataSourceName": "",
          "AutoRuleBindingEnabled": false,
          "AutoRuleBindingString": "",
          "InvariantPropertyName": "Fontsizes",
          "IsLockable": false,
          "NameMapSourceSchema": "?"
        },
        {
          "AFDDataSourceName": "",
          "AutoRuleBindingEnabled": false,
          "AutoRuleBindingString": "true",
          "InvariantPropertyName": "DarkMode",
          "IsLockable": false,
          "NameMapSourceSchema": "?"
        }
      ],
      "HasDynamicProperties": false,
      "IsAutoGenerated": false,
      "IsComponentDefinition": false,
      "IsDataControl": false,
      "IsFromScreenLayout": false,
      "IsGroupControl": false,
      "IsLocked": false,
      "LayoutName": "",
      "Metadata": {
        "AllowAccessToGlobals": false,
        "AllowCustomization": true,
        "Description": "ボタン"
      },
      "MetaDataIDKey": "",
      "Name": "Button_6",
      "ParentIndex": 3,
      "PersistMetaDataIDKey": false,
      "Properties": [
        {
          "Category": "Data",
          "PropertyName": "IconName",
          "RuleProviderType": "Unknown"
        },
        {
          "Category": "Data",
          "PropertyName": "LinealGradientColor2",
          "RuleProviderType": "Unknown"
        },
        {
          "Category": "Data",
          "PropertyName": "LinealGradientColor1",
          "RuleProviderType": "Unknown"
        },
        {
          "Category": "Data",
          "PropertyName": "LinealGradient",
          "RuleProviderType": "System"
        },
        {
          "Category": "Data",
          "PropertyName": "IconColour",
          "RuleProviderType": "System"
        },
        {
          "Category": "Data",
          "PropertyName": "IconColorActive",
          "RuleProviderType": "System"
        },
        {
          "Category": "Data",
          "PropertyName": "BorderRadius",
          "RuleProviderType": "System"
        },
        {
          "Category": "Data",
          "PropertyName": "ButtonSelected",
          "RuleProviderType": "System"
        },
        {
          "Category": "Data",
          "PropertyName": "icontext",
          "RuleProviderType": "Unknown"
        },
        {
          "Category": "Data",
          "PropertyName": "TextInput",
          "RuleProviderType": "Unknown"
        },
        {
          "Category": "Data",
          "PropertyName": "Fontsizes",
          "RuleProviderType": "Unknown"
        },
        {
          "Category": "Data",
          "PropertyName": "DarkMode",
          "RuleProviderType": "Unknown"
        },
        {
          "Category": "Design",
          "PropertyName": "Height",
          "RuleProviderType": "Unknown"
        },
        {
          "Category": "Design",
          "PropertyName": "Width",
          "RuleProviderType": "Unknown"
        },
        {
          "Category": "Design",
          "PropertyName": "X",
          "RuleProviderType": "Unknown"
        },
        {
          "Category": "Design",
          "PropertyName": "Y",
          "RuleProviderType": "Unknown"
        },
        {
          "Category": "Design",
          "PropertyName": "ZIndex",
          "RuleProviderType": "Unknown"
        },
        {
          "Category": "Design",
          "PropertyName": "Fill",
          "RuleProviderType": "System"
        },
        {
          "Category": "Behavior",
          "PropertyName": "OnSelect",
          "RuleProviderType": "Unknown"
        }
      ],
      "StyleName": "",
      "Type": "ControlInfo"
    },
    "Container1": {
      "AllowAccessToGlobals": true,
      "ControlPropertyState": [
        "BorderColor",
        "BorderStyle",
        "Fill",
        "X",
        "Y",
        "Width",
        "Height",
        "DisplayMode",
        "LayoutMode",
        "LayoutDirection",
        "LayoutAlignItems",
        "LayoutJustifyContent",
        "LayoutGap",
        "LayoutOverflowX",
        "LayoutOverflowY",
        "LayoutWrap",
        "DropShadow",
        "ZIndex",
        "RadiusTopLeft",
        "RadiusTopRight",
        "RadiusBottomLeft",
        "RadiusBottomRight",
        {
          "AFDDataSourceName": "",
          "AutoRuleBindingEnabled": false,
          "AutoRuleBindingString": "",
          "InvariantPropertyName": "Visible",
          "IsLockable": false,
          "NameMapSourceSchema": "?"
        }
      ],
      "HasDynamicProperties": false,
      "IsAutoGenerated": false,
      "IsComponentDefinition": false,
      "IsDataControl": false,
      "IsFromScreenLayout": false,
      "IsGroupControl": false,
      "IsLocked": false,
      "LayoutName": "",
      "MetaDataIDKey": "",
      "Name": "Container1",
      "ParentIndex": 0,
      "PersistMetaDataIDKey": false,
      "Properties": [
        {
          "Category": "Design",
          "PropertyName": "BorderColor",
          "RuleProviderType": "Unknown"
        },
        {
          "Category": "Design",
          "PropertyName": "BorderStyle",
          "RuleProviderType": "Unknown"
        },
        {
          "Category": "Design",
          "PropertyName": "Fill",
          "RuleProviderType": "Unknown"
        },
        {
          "Category": "Design",
          "PropertyName": "X",
          "RuleProviderType": "Unknown"
        },
        {
          "Category": "Design",
          "PropertyName": "Y",
          "RuleProviderType": "Unknown"
        },
        {
          "Category": "Design",
          "PropertyName": "Width",
          "RuleProviderType": "Unknown"
        },
        {
          "Category": "Design",
          "PropertyName": "Height",
          "RuleProviderType": "Unknown"
        },
        {
          "Category": "Design",
          "PropertyName": "DisplayMode",
          "RuleProviderType": "Unknown"
        },
        {
          "Category": "Design",
          "PropertyName": "LayoutMode",
          "RuleProviderType": "Unknown"
        },
        {
          "Category": "Design",
          "PropertyName": "LayoutDirection",
          "RuleProviderType": "Unknown"
        },
        {
          "Category": "Design",
          "PropertyName": "LayoutAlignItems",
          "RuleProviderType": "Unknown"
        },
        {
          "Category": "Design",
          "PropertyName": "LayoutJustifyContent",
          "RuleProviderType": "Unknown"
        },
        {
          "Category": "Design",
          "PropertyName": "LayoutGap",
          "RuleProviderType": "Unknown"
        },
        {
          "Category": "Design",
          "PropertyName": "LayoutOverflowX",
          "RuleProviderType": "Unknown"
        },
        {
          "Category": "Design",
          "PropertyName": "LayoutOverflowY",
          "RuleProviderType": "Unknown"
        },
        {
          "Category": "Design",
          "PropertyName": "LayoutWrap",
          "RuleProviderType": "Unknown"
        },
        {
          "Category": "Design",
          "PropertyName": "DropShadow",
          "RuleProviderType": "Unknown"
        },
        {
          "Category": "Design",
          "PropertyName": "ZIndex",
          "RuleProviderType": "Unknown"
        },
        {
          "Category": "Design",
          "PropertyName": "RadiusTopLeft",
          "RuleProviderType": "Unknown"
        },
        {
          "Category": "Design",
          "PropertyName": "RadiusTopRight",
          "RuleProviderType": "Unknown"
        },
        {
          "Category": "Design",
          "PropertyName": "RadiusBottomLeft",
          "RuleProviderType": "Unknown"
        },
        {
          "Category": "Design",
          "PropertyName": "RadiusBottomRight",
          "RuleProviderType": "Unknown"
        },
        {
          "Category": "Design",
          "PropertyName": "Visible",
          "RuleProviderType": "Unknown"
        }
      ],
      "StyleName": "defaultGroupContainerStyle",
      "Type": "ControlInfo"
    },
    "Label1": {
      "AllowAccessToGlobals": true,
      "ControlPropertyState": [
        "Live",
        "Overflow",
        {
          "AFDDataSourceName": "",
          "AutoRuleBindingEnabled": false,
          "AutoRuleBindingString": "",
          "InvariantPropertyName": "Text",
          "IsLockable": false,
          "NameMapSourceSchema": "?"
        },
        "Role",
        {
          "AFDDataSourceName": "",
          "AutoRuleBindingEnabled": false,
          "AutoRuleBindingString": "RGBA(0, 0, 0, 1)",
          "InvariantPropertyName": "Color",
          "IsLockable": false,
          "NameMapSourceSchema": "?"
        },
        "DisabledColor",
        "PressedColor",
        "HoverColor",
        "BorderColor",
        "DisabledBorderColor",
        "PressedBorderColor",
        "HoverBorderColor",
        "BorderStyle",
        "FocusedBorderColor",
        "Fill",
        "DisabledFill",
        "PressedFill",
        "HoverFill",
        {
          "AFDDataSourceName": "",
          "AutoRuleBindingEnabled": false,
          "AutoRuleBindingString": "",
          "InvariantPropertyName": "Font",
          "IsLockable": false,
          "NameMapSourceSchema": "?"
        },
        "FontWeight",
        {
          "AFDDataSourceName": "",
          "AutoRuleBindingEnabled": false,
          "AutoRuleBindingString": "",
          "InvariantPropertyName": "Align",
          "IsLockable": false,
          "NameMapSourceSchema": "?"
        },
        "VerticalAlign",
        "X",
        "Y",
        {
          "AFDDataSourceName": "",
          "AutoRuleBindingEnabled": false,
          "AutoRuleBindingString": "550",
          "InvariantPropertyName": "Width",
          "IsLockable": false,
          "NameMapSourceSchema": "?"
        },
        "Height",
        "DisplayMode",
        "ZIndex",
        "LineHeight",
        "BorderThickness",
        "FocusedBorderThickness",
        {
          "AFDDataSourceName": "",
          "AutoRuleBindingEnabled": false,
          "AutoRuleBindingString": "",
          "InvariantPropertyName": "Size",
          "IsLockable": false,
          "NameMapSourceSchema": "?"
        },
        "Italic",
        "Underline",
        "Strikethrough",
        "PaddingTop",
        "PaddingRight",
        "PaddingBottom",
        "PaddingLeft"
      ],
      "HasDynamicProperties": false,
      "IsAutoGenerated": false,
      "IsComponentDefinition": false,
      "IsDataControl": false,
      "IsFromScreenLayout": false,
      "IsGroupControl": false,
      "IsLocked": false,
      "LayoutName": "",
      "MetaDataIDKey": "",
      "Name": "Label1",
      "ParentIndex": 3,
      "PersistMetaDataIDKey": false,
      "Properties": [
        {
          "Category": "Data",
          "PropertyName": "Live",
          "RuleProviderType": "Unknown"
        },
        {
          "Category": "Data",
          "PropertyName": "Text",
          "RuleProviderType": "Unknown"
        },
        {
          "Category": "Data",
          "PropertyName": "Role",
          "RuleProviderType": "Unknown"
        },
        {
          "Category": "Design",
          "PropertyName": "Overflow",
          "RuleProviderType": "Unknown"
        },
        {
          "Category": "Design",
          "PropertyName": "Color",
          "RuleProviderType": "Unknown"
        },
        {
          "Category": "Design",
          "PropertyName": "DisabledColor",
          "RuleProviderType": "Unknown"
        },
        {
          "Category": "Design",
          "PropertyName": "PressedColor",
          "RuleProviderType": "Unknown"
        },
        {
          "Category": "Design",
          "PropertyName": "HoverColor",
          "RuleProviderType": "Unknown"
        },
        {
          "Category": "Design",
          "PropertyName": "BorderColor",
          "RuleProviderType": "Unknown"
        },
        {
          "Category": "Design",
          "PropertyName": "DisabledBorderColor",
          "RuleProviderType": "Unknown"
        },
        {
          "Category": "Design",
          "PropertyName": "PressedBorderColor",
          "RuleProviderType": "Unknown"
        },
        {
          "Category": "Design",
          "PropertyName": "HoverBorderColor",
          "RuleProviderType": "Unknown"
        },
        {
          "Category": "Design",
          "PropertyName": "BorderStyle",
          "RuleProviderType": "Unknown"
        },
        {
          "Category": "Design",
          "PropertyName": "FocusedBorderColor",
          "RuleProviderType": "Unknown"
        },
        {
          "Category": "Design",
          "PropertyName": "Fill",
          "RuleProviderType": "Unknown"
        },
        {
          "Category": "Design",
          "PropertyName": "DisabledFill",
          "RuleProviderType": "Unknown"
        },
        {
          "Category": "Design",
          "PropertyName": "PressedFill",
          "RuleProviderType": "Unknown"
        },
        {
          "Category": "Design",
          "PropertyName": "HoverFill",
          "RuleProviderType": "Unknown"
        },
        {
          "Category": "Design",
          "PropertyName": "Font",
          "RuleProviderType": "Unknown"
        },
        {
          "Category": "Design",
          "PropertyName": "FontWeight",
          "RuleProviderType": "Unknown"
        },
        {
          "Category": "Design",
          "PropertyName": "Align",
          "RuleProviderType": "Unknown"
        },
        {
          "Category": "Design",
          "PropertyName": "VerticalAlign",
          "RuleProviderType": "Unknown"
        },
        {
          "Category": "Design",
          "PropertyName": "X",
          "RuleProviderType": "Unknown"
        },
        {
          "Category": "Design",
          "PropertyName": "Y",
          "RuleProviderType": "Unknown"
        },
        {
          "Category": "Design",
          "PropertyName": "Width",
          "RuleProviderType": "Unknown"
        },
        {
          "Category": "Design",
          "PropertyName": "Height",
          "RuleProviderType": "Unknown"
        },
        {
          "Category": "Design",
          "PropertyName": "DisplayMode",
          "RuleProviderType": "Unknown"
        },
        {
          "Category": "Design",
          "PropertyName": "ZIndex",
          "RuleProviderType": "Unknown"
        },
        {
          "Category": "Design",
          "PropertyName": "LineHeight",
          "RuleProviderType": "Unknown"
        },
        {
          "Category": "Design",
          "PropertyName": "BorderThickness",
          "RuleProviderType": "Unknown"
        },
        {
          "Category": "Design",
          "PropertyName": "FocusedBorderThickness",
          "RuleProviderType": "Unknown"
        },
        {
          "Category": "Design",
          "PropertyName": "Size",
          "RuleProviderType": "Unknown"
        },
        {
          "Category": "Design",
          "PropertyName": "Italic",
          "RuleProviderType": "Unknown"
        },
        {
          "Category": "Design",
          "PropertyName": "Underline",
          "RuleProviderType": "Unknown"
        },
        {
          "Category": "Design",
          "PropertyName": "Strikethrough",
          "RuleProviderType": "Unknown"
        },
        {
          "Category": "Design",
          "PropertyName": "PaddingTop",
          "RuleProviderType": "Unknown"
        },
        {
          "Category": "Design",
          "PropertyName": "PaddingRight",
          "RuleProviderType": "Unknown"
        },
        {
          "Category": "Design",
          "PropertyName": "PaddingBottom",
          "RuleProviderType": "Unknown"
        },
        {
          "Category": "Design",
          "PropertyName": "PaddingLeft",
          "RuleProviderType": "Unknown"
        }
      ],
      "StyleName": "defaultLabelStyle",
      "Type": "ControlInfo"
    },
    "LinearGradient_Generator_HEX_1": {
      "AllowAccessToGlobals": true,
      "ControlPropertyState": [
        "Fill",
        {
          "AFDDataSourceName": "",
          "AutoRuleBindingEnabled": false,
          "AutoRuleBindingString": "",
          "InvariantPropertyName": "Height",
          "IsLockable": false,
          "NameMapSourceSchema": "?"
        },
        {
          "AFDDataSourceName": "",
          "AutoRuleBindingEnabled": false,
          "AutoRuleBindingString": "",
          "InvariantPropertyName": "Width",
          "IsLockable": false,
          "NameMapSourceSchema": "?"
        },
        "X",
        "Y",
        "ZIndex",
        {
          "AFDDataSourceName": "",
          "AutoRuleBindingEnabled": false,
          "AutoRuleBindingString": "true",
          "InvariantPropertyName": "DarkMode",
          "IsLockable": false,
          "NameMapSourceSchema": "?"
        },
        {
          "AFDDataSourceName": "",
          "AutoRuleBindingEnabled": false,
          "AutoRuleBindingString": "\"テキスト\"",
          "InvariantPropertyName": "IconLinealGradient1",
          "IsLockable": false,
          "NameMapSourceSchema": "?"
        },
        {
          "AFDDataSourceName": "",
          "AutoRuleBindingEnabled": false,
          "AutoRuleBindingString": "\"テキスト\"",
          "InvariantPropertyName": "IconLinealGradient2",
          "IsLockable": false,
          "NameMapSourceSchema": "?"
        },
        "Borderradius",
        {
          "AFDDataSourceName": "",
          "AutoRuleBindingEnabled": false,
          "AutoRuleBindingString": "\"テキスト\"",
          "InvariantPropertyName": "G_GL1",
          "IsLockable": false,
          "NameMapSourceSchema": "?"
        },
        {
          "AFDDataSourceName": "",
          "AutoRuleBindingEnabled": false,
          "AutoRuleBindingString": "\"テキスト\"",
          "InvariantPropertyName": "G_GL2",
          "IsLockable": false,
          "NameMapSourceSchema": "?"
        }
      ],
      "HasDynamicProperties": false,
      "IsAutoGenerated": false,
      "IsComponentDefinition": false,
      "IsDataControl": false,
      "IsFromScreenLayout": false,
      "IsGroupControl": false,
      "IsLocked": false,
      "LayoutName": "",
      "Metadata": {
        "AllowAccessToGlobals": false,
        "AllowCustomization": true,
        "Description": ""
      },
      "MetaDataIDKey": "",
      "Name": "LinearGradient_Generator_HEX_1",
      "ParentIndex": 2,
      "PersistMetaDataIDKey": false,
      "Properties": [
        {
          "Category": "Data",
          "PropertyName": "DarkMode",
          "RuleProviderType": "Unknown"
        },
        {
          "Category": "Data",
          "PropertyName": "IconLinealGradient1",
          "RuleProviderType": "System"
        },
        {
          "Category": "Data",
          "PropertyName": "IconLinealGradient2",
          "RuleProviderType": "System"
        },
        {
          "Category": "Data",
          "PropertyName": "Borderradius",
          "RuleProviderType": "System"
        },
        {
          "Category": "Data",
          "PropertyName": "G_GL1",
          "RuleProviderType": "System"
        },
        {
          "Category": "Data",
          "PropertyName": "G_GL2",
          "RuleProviderType": "System"
        },
        {
          "Category": "Design",
          "PropertyName": "ZIndex",
          "RuleProviderType": "Unknown"
        },
        {
          "Category": "Design",
          "PropertyName": "Y",
          "RuleProviderType": "Unknown"
        },
        {
          "Category": "Design",
          "PropertyName": "X",
          "RuleProviderType": "Unknown"
        },
        {
          "Category": "Design",
          "PropertyName": "Width",
          "RuleProviderType": "Unknown"
        },
        {
          "Category": "Design",
          "PropertyName": "Height",
          "RuleProviderType": "Unknown"
        },
        {
          "Category": "Design",
          "PropertyName": "Fill",
          "RuleProviderType": "System"
        }
      ],
      "StyleName": "",
      "Type": "ControlInfo"
    },
    "LinearGradient_Generator_RGBA_1": {
      "AllowAccessToGlobals": true,
      "ControlPropertyState": [
        "Fill",
        "Height",
        {
          "AFDDataSourceName": "",
          "AutoRuleBindingEnabled": false,
          "AutoRuleBindingString": "",
          "InvariantPropertyName": "Width",
          "IsLockable": false,
          "NameMapSourceSchema": "?"
        },
        "X",
        "Y",
        "ZIndex",
        {
          "AFDDataSourceName": "",
          "AutoRuleBindingEnabled": false,
          "AutoRuleBindingString": "true",
          "InvariantPropertyName": "DarkMode",
          "IsLockable": false,
          "NameMapSourceSchema": "?"
        },
        "borderradius",
        {
          "AFDDataSourceName": "",
          "AutoRuleBindingEnabled": false,
          "AutoRuleBindingString": "\"テキスト\"",
          "InvariantPropertyName": "IconLinealGradient1",
          "IsLockable": false,
          "NameMapSourceSchema": "?"
        },
        {
          "AFDDataSourceName": "",
          "AutoRuleBindingEnabled": false,
          "AutoRuleBindingString": "\"テキスト\"",
          "InvariantPropertyName": "IconLinealGradient2",
          "IsLockable": false,
          "NameMapSourceSchema": "?"
        },
        {
          "AFDDataSourceName": "",
          "AutoRuleBindingEnabled": false,
          "AutoRuleBindingString": "\"テキスト\"",
          "InvariantPropertyName": "G_GL1",
          "IsLockable": false,
          "NameMapSourceSchema": "?"
        },
        {
          "AFDDataSourceName": "",
          "AutoRuleBindingEnabled": false,
          "AutoRuleBindingString": "\"テキスト\"",
          "InvariantPropertyName": "G_GL2",
          "IsLockable": false,
          "NameMapSourceSchema": "?"
        }
      ],
      "HasDynamicProperties": false,
      "IsAutoGenerated": false,
      "IsComponentDefinition": false,
      "IsDataControl": false,
      "IsFromScreenLayout": false,
      "IsGroupControl": false,
      "IsLocked": false,
      "LayoutName": "",
      "Metadata": {
        "AllowAccessToGlobals": false,
        "AllowCustomization": true,
        "Description": ""
      },
      "MetaDataIDKey": "",
      "Name": "LinearGradient_Generator_RGBA_1",
      "ParentIndex": 1,
      "PersistMetaDataIDKey": false,
      "Properties": [
        {
          "Category": "Data",
          "PropertyName": "IconLinealGradient2",
          "RuleProviderType": "System"
        },
        {
          "Category": "Data",
          "PropertyName": "IconLinealGradient1",
          "RuleProviderType": "System"
        },
        {
          "Category": "Data",
          "PropertyName": "borderradius",
          "RuleProviderType": "System"
        },
        {
          "Category": "Data",
          "PropertyName": "DarkMode",
          "RuleProviderType": "Unknown"
        },
        {
          "Category": "Data",
          "PropertyName": "G_GL1",
          "RuleProviderType": "System"
        },
        {
          "Category": "Data",
          "PropertyName": "G_GL2",
          "RuleProviderType": "System"
        },
        {
          "Category": "Design",
          "PropertyName": "ZIndex",
          "RuleProviderType": "Unknown"
        },
        {
          "Category": "Design",
          "PropertyName": "Y",
          "RuleProviderType": "Unknown"
        },
        {
          "Category": "Design",
          "PropertyName": "X",
          "RuleProviderType": "Unknown"
        },
        {
          "Category": "Design",
          "PropertyName": "Width",
          "RuleProviderType": "Unknown"
        },
        {
          "Category": "Design",
          "PropertyName": "Height",
          "RuleProviderType": "Unknown"
        },
        {
          "Category": "Design",
          "PropertyName": "Fill",
          "RuleProviderType": "System"
        }
      ],
      "StyleName": "",
      "Type": "ControlInfo"
    },
    "NeonGlowNavMenu_2": {
      "AllowAccessToGlobals": true,
      "ControlPropertyState": [
        "Fill",
        {
          "AFDDataSourceName": "",
          "AutoRuleBindingEnabled": false,
          "AutoRuleBindingString": "",
          "InvariantPropertyName": "Height",
          "IsLockable": false,
          "NameMapSourceSchema": "?"
        },
        {
          "AFDDataSourceName": "",
          "AutoRuleBindingEnabled": false,
          "AutoRuleBindingString": "",
          "InvariantPropertyName": "Width",
          "IsLockable": false,
          "NameMapSourceSchema": "?"
        },
        "X",
        {
          "AFDDataSourceName": "",
          "AutoRuleBindingEnabled": false,
          "AutoRuleBindingString": "",
          "InvariantPropertyName": "Y",
          "IsLockable": false,
          "NameMapSourceSchema": "?"
        },
        "ZIndex",
        {
          "AFDDataSourceName": "",
          "AutoRuleBindingEnabled": false,
          "AutoRuleBindingString": "Table(\n    {\n        //this is the name of the screen\nMenuItem: \"Home\",\n        // this is the screen you will navigate to when you select this item\n        MenuScreenNavigate: App.ActiveScreen,\n        //if you are not comfortable with SVG's, you can use standard icons instead!  - just make sure you change the icon property of MenuIcon to ThisItem.StandardIcon\n        StandardIcon: Icon.Home,\n        ID: 1\n    },\n\n    {\n        MenuItem: \"Profile\",\n        MenuScreenNavigate: App.ActiveScreen,\n\n        StandardIcon: Icon.AddUser,\n        ID: 2\n    },\n    {\n        MenuItem: \"Settings\",\n        MenuScreenNavigate: App.ActiveScreen,\n        StandardIcon: Icon.Settings,\n        ID: 3\n    },\n\n    {\n        MenuItem: \"Balance\",\n        MenuScreenNavigate: App.ActiveScreen,\n        StandardIcon: Icon.AddDocument,\n        ID: 4\n    }\n)",
          "InvariantPropertyName": "MenuItems",
          "IsLockable": false,
          "NameMapSourceSchema": "?"
        },
        "IconsSVGorStandard",
        {
          "AFDDataSourceName": "",
          "AutoRuleBindingEnabled": false,
          "AutoRuleBindingString": "\"テキスト\"",
          "InvariantPropertyName": "SVGActiveIconColour",
          "IsLockable": false,
          "NameMapSourceSchema": "?"
        },
        "StandardIconColour",
        {
          "AFDDataSourceName": "",
          "AutoRuleBindingEnabled": false,
          "AutoRuleBindingString": "\"テキスト\"",
          "InvariantPropertyName": "SVGActiveIconColour2",
          "IsLockable": false,
          "NameMapSourceSchema": "?"
        },
        {
          "AFDDataSourceName": "",
          "AutoRuleBindingEnabled": false,
          "AutoRuleBindingString": "true",
          "InvariantPropertyName": "DarkMode",
          "IsLockable": false,
          "NameMapSourceSchema": "?"
        },
        "inversion",
        {
          "AFDDataSourceName": "",
          "AutoRuleBindingEnabled": false,
          "AutoRuleBindingString": "true",
          "InvariantPropertyName": "selectedID",
          "IsLockable": false,
          "NameMapSourceSchema": "?"
        }
      ],
      "HasDynamicProperties": false,
      "IsAutoGenerated": false,
      "IsComponentDefinition": false,
      "IsDataControl": false,
      "IsFromScreenLayout": false,
      "IsGroupControl": false,
      "IsLocked": false,
      "LayoutName": "",
      "Metadata": {
        "AllowAccessToGlobals": false,
        "AllowCustomization": true,
        "Description": ""
      },
      "MetaDataIDKey": "",
      "Name": "NeonGlowNavMenu_2",
      "ParentIndex": 8,
      "PersistMetaDataIDKey": false,
      "Properties": [
        {
          "Category": "Data",
          "PropertyName": "IconsSVGorStandard",
          "RuleProviderType": "System"
        },
        {
          "Category": "Data",
          "PropertyName": "MenuItems",
          "RuleProviderType": "Unknown"
        },
        {
          "Category": "Data",
          "PropertyName": "SVGActiveIconColour",
          "RuleProviderType": "Unknown"
        },
        {
          "Category": "Data",
          "PropertyName": "StandardIconColour",
          "RuleProviderType": "System"
        },
        {
          "Category": "Data",
          "PropertyName": "SVGActiveIconColour2",
          "RuleProviderType": "Unknown"
        },
        {
          "Category": "Data",
          "PropertyName": "DarkMode",
          "RuleProviderType": "Unknown"
        },
        {
          "Category": "Data",
          "PropertyName": "inversion",
          "RuleProviderType": "System"
        },
        {
          "Category": "Data",
          "PropertyName": "selectedID",
          "RuleProviderType": "System"
        },
        {
          "Category": "Design",
          "PropertyName": "Width",
          "RuleProviderType": "Unknown"
        },
        {
          "Category": "Design",
          "PropertyName": "Height",
          "RuleProviderType": "Unknown"
        },
        {
          "Category": "Design",
          "PropertyName": "Fill",
          "RuleProviderType": "System"
        },
        {
          "Category": "Design",
          "PropertyName": "ZIndex",
          "RuleProviderType": "Unknown"
        },
        {
          "Category": "Design",
          "PropertyName": "Y",
          "RuleProviderType": "Unknown"
        },
        {
          "Category": "Design",
          "PropertyName": "X",
          "RuleProviderType": "Unknown"
        }
      ],
      "StyleName": "",
      "Type": "ControlInfo"
    },
    "Slider_3": {
      "AllowAccessToGlobals": true,
      "ControlPropertyState": [
        {
          "AFDDataSourceName": "",
          "AutoRuleBindingEnabled": false,
          "AutoRuleBindingString": "",
          "InvariantPropertyName": "Fill",
          "IsLockable": false,
          "NameMapSourceSchema": "?"
        },
        {
          "AFDDataSourceName": "",
          "AutoRuleBindingEnabled": false,
          "AutoRuleBindingString": "",
          "InvariantPropertyName": "Height",
          "IsLockable": false,
          "NameMapSourceSchema": "?"
        },
        {
          "AFDDataSourceName": "",
          "AutoRuleBindingEnabled": false,
          "AutoRuleBindingString": "",
          "InvariantPropertyName": "Width",
          "IsLockable": false,
          "NameMapSourceSchema": "?"
        },
        "X",
        "Y",
        "ZIndex",
        {
          "AFDDataSourceName": "",
          "AutoRuleBindingEnabled": false,
          "AutoRuleBindingString": "100",
          "InvariantPropertyName": "Value",
          "IsLockable": false,
          "NameMapSourceSchema": "?"
        },
        "Max",
        "Min",
        {
          "AFDDataSourceName": "",
          "AutoRuleBindingEnabled": false,
          "AutoRuleBindingString": "\"#2c3e50\"",
          "InvariantPropertyName": "LinealGradientColour1",
          "IsLockable": false,
          "NameMapSourceSchema": "?"
        },
        {
          "AFDDataSourceName": "",
          "AutoRuleBindingEnabled": false,
          "AutoRuleBindingString": "\"#3498db\"",
          "InvariantPropertyName": "LinealGradientColour2",
          "IsLockable": false,
          "NameMapSourceSchema": "?"
        },
        "borderradius",
        {
          "AFDDataSourceName": "",
          "AutoRuleBindingEnabled": false,
          "AutoRuleBindingString": "true",
          "InvariantPropertyName": "DarkMode",
          "IsLockable": false,
          "NameMapSourceSchema": "?"
        }
      ],
      "HasDynamicProperties": false,
      "IsAutoGenerated": false,
      "IsComponentDefinition": false,
      "IsDataControl": false,
      "IsFromScreenLayout": false,
      "IsGroupControl": false,
      "IsLocked": false,
      "LayoutName": "",
      "Metadata": {
        "AllowAccessToGlobals": false,
        "AllowCustomization": true,
        "Description": "スライダー"
      },
      "MetaDataIDKey": "",
      "Name": "Slider_3",
      "ParentIndex": 2,
      "PersistMetaDataIDKey": false,
      "Properties": [
        {
          "Category": "Data",
          "PropertyName": "Min",
          "RuleProviderType": "System"
        },
        {
          "Category": "Data",
          "PropertyName": "Max",
          "RuleProviderType": "System"
        },
        {
          "Category": "Data",
          "PropertyName": "Value",
          "RuleProviderType": "System"
        },
        {
          "Category": "Data",
          "PropertyName": "LinealGradientColour1",
          "RuleProviderType": "Unknown"
        },
        {
          "Category": "Data",
          "PropertyName": "LinealGradientColour2",
          "RuleProviderType": "Unknown"
        },
        {
          "Category": "Data",
          "PropertyName": "borderradius",
          "RuleProviderType": "System"
        },
        {
          "Category": "Data",
          "PropertyName": "DarkMode",
          "RuleProviderType": "Unknown"
        },
        {
          "Category": "Design",
          "PropertyName": "ZIndex",
          "RuleProviderType": "Unknown"
        },
        {
          "Category": "Design",
          "PropertyName": "Fill",
          "RuleProviderType": "System"
        },
        {
          "Category": "Design",
          "PropertyName": "Height",
          "RuleProviderType": "Unknown"
        },
        {
          "Category": "Design",
          "PropertyName": "Y",
          "RuleProviderType": "Unknown"
        },
        {
          "Category": "Design",
          "PropertyName": "X",
          "RuleProviderType": "Unknown"
        },
        {
          "Category": "Design",
          "PropertyName": "Width",
          "RuleProviderType": "Unknown"
        }
      ],
      "StyleName": "",
      "Type": "ControlInfo"
    },
    "Slider_4": {
      "AllowAccessToGlobals": true,
      "ControlPropertyState": [
        {
          "AFDDataSourceName": "",
          "AutoRuleBindingEnabled": false,
          "AutoRuleBindingString": "",
          "InvariantPropertyName": "Fill",
          "IsLockable": false,
          "NameMapSourceSchema": "?"
        },
        {
          "AFDDataSourceName": "",
          "AutoRuleBindingEnabled": false,
          "AutoRuleBindingString": "",
          "InvariantPropertyName": "Height",
          "IsLockable": false,
          "NameMapSourceSchema": "?"
        },
        {
          "AFDDataSourceName": "",
          "AutoRuleBindingEnabled": false,
          "AutoRuleBindingString": "",
          "InvariantPropertyName": "Width",
          "IsLockable": false,
          "NameMapSourceSchema": "?"
        },
        "X",
        "Y",
        "ZIndex",
        {
          "AFDDataSourceName": "",
          "AutoRuleBindingEnabled": false,
          "AutoRuleBindingString": "100",
          "InvariantPropertyName": "Value",
          "IsLockable": false,
          "NameMapSourceSchema": "?"
        },
        "Max",
        "Min",
        {
          "AFDDataSourceName": "",
          "AutoRuleBindingEnabled": false,
          "AutoRuleBindingString": "\"#2c3e50\"",
          "InvariantPropertyName": "LinealGradientColour1",
          "IsLockable": false,
          "NameMapSourceSchema": "?"
        },
        {
          "AFDDataSourceName": "",
          "AutoRuleBindingEnabled": false,
          "AutoRuleBindingString": "\"#3498db\"",
          "InvariantPropertyName": "LinealGradientColour2",
          "IsLockable": false,
          "NameMapSourceSchema": "?"
        },
        "borderradius",
        {
          "AFDDataSourceName": "",
          "AutoRuleBindingEnabled": false,
          "AutoRuleBindingString": "true",
          "InvariantPropertyName": "DarkMode",
          "IsLockable": false,
          "NameMapSourceSchema": "?"
        }
      ],
      "HasDynamicProperties": false,
      "IsAutoGenerated": false,
      "IsComponentDefinition": false,
      "IsDataControl": false,
      "IsFromScreenLayout": false,
      "IsGroupControl": false,
      "IsLocked": false,
      "LayoutName": "",
      "Metadata": {
        "AllowAccessToGlobals": false,
        "AllowCustomization": true,
        "Description": "スライダー"
      },
      "MetaDataIDKey": "",
      "Name": "Slider_4",
      "ParentIndex": 6,
      "PersistMetaDataIDKey": false,
      "Properties": [
        {
          "Category": "Data",
          "PropertyName": "Min",
          "RuleProviderType": "System"
        },
        {
          "Category": "Data",
          "PropertyName": "Max",
          "RuleProviderType": "System"
        },
        {
          "Category": "Data",
          "PropertyName": "Value",
          "RuleProviderType": "System"
        },
        {
          "Category": "Data",
          "PropertyName": "LinealGradientColour1",
          "RuleProviderType": "Unknown"
        },
        {
          "Category": "Data",
          "PropertyName": "LinealGradientColour2",
          "RuleProviderType": "Unknown"
        },
        {
          "Category": "Data",
          "PropertyName": "borderradius",
          "RuleProviderType": "System"
        },
        {
          "Category": "Data",
          "PropertyName": "DarkMode",
          "RuleProviderType": "Unknown"
        },
        {
          "Category": "Design",
          "PropertyName": "ZIndex",
          "RuleProviderType": "Unknown"
        },
        {
          "Category": "Design",
          "PropertyName": "Fill",
          "RuleProviderType": "System"
        },
        {
          "Category": "Design",
          "PropertyName": "Height",
          "RuleProviderType": "Unknown"
        },
        {
          "Category": "Design",
          "PropertyName": "Y",
          "RuleProviderType": "Unknown"
        },
        {
          "Category": "Design",
          "PropertyName": "X",
          "RuleProviderType": "Unknown"
        },
        {
          "Category": "Design",
          "PropertyName": "Width",
          "RuleProviderType": "Unknown"
        }
      ],
      "StyleName": "",
      "Type": "ControlInfo"
    },
    "Slider_5": {
      "AllowAccessToGlobals": true,
      "ControlPropertyState": [
        {
          "AFDDataSourceName": "",
          "AutoRuleBindingEnabled": false,
          "AutoRuleBindingString": "",
          "InvariantPropertyName": "Fill",
          "IsLockable": false,
          "NameMapSourceSchema": "?"
        },
        {
          "AFDDataSourceName": "",
          "AutoRuleBindingEnabled": false,
          "AutoRuleBindingString": "",
          "InvariantPropertyName": "Height",
          "IsLockable": false,
          "NameMapSourceSchema": "?"
        },
        {
          "AFDDataSourceName": "",
          "AutoRuleBindingEnabled": false,
          "AutoRuleBindingString": "",
          "InvariantPropertyName": "Width",
          "IsLockable": false,
          "NameMapSourceSchema": "?"
        },
        "X",
        "Y",
        "ZIndex",
        {
          "AFDDataSourceName": "",
          "AutoRuleBindingEnabled": false,
          "AutoRuleBindingString": "100",
          "InvariantPropertyName": "Value",
          "IsLockable": false,
          "NameMapSourceSchema": "?"
        },
        "Max",
        "Min",
        {
          "AFDDataSourceName": "",
          "AutoRuleBindingEnabled": false,
          "AutoRuleBindingString": "\"#2c3e50\"",
          "InvariantPropertyName": "LinealGradientColour1",
          "IsLockable": false,
          "NameMapSourceSchema": "?"
        },
        {
          "AFDDataSourceName": "",
          "AutoRuleBindingEnabled": false,
          "AutoRuleBindingString": "\"#3498db\"",
          "InvariantPropertyName": "LinealGradientColour2",
          "IsLockable": false,
          "NameMapSourceSchema": "?"
        },
        "borderradius",
        {
          "AFDDataSourceName": "",
          "AutoRuleBindingEnabled": false,
          "AutoRuleBindingString": "true",
          "InvariantPropertyName": "DarkMode",
          "IsLockable": false,
          "NameMapSourceSchema": "?"
        }
      ],
      "HasDynamicProperties": false,
      "IsAutoGenerated": false,
      "IsComponentDefinition": false,
      "IsDataControl": false,
      "IsFromScreenLayout": false,
      "IsGroupControl": false,
      "IsLocked": false,
      "LayoutName": "",
      "Metadata": {
        "AllowAccessToGlobals": false,
        "AllowCustomization": true,
        "Description": "スライダー"
      },
      "MetaDataIDKey": "",
      "Name": "Slider_5",
      "ParentIndex": 1,
      "PersistMetaDataIDKey": false,
      "Properties": [
        {
          "Category": "Data",
          "PropertyName": "Min",
          "RuleProviderType": "System"
        },
        {
          "Category": "Data",
          "PropertyName": "Max",
          "RuleProviderType": "System"
        },
        {
          "Category": "Data",
          "PropertyName": "Value",
          "RuleProviderType": "System"
        },
        {
          "Category": "Data",
          "PropertyName": "LinealGradientColour1",
          "RuleProviderType": "Unknown"
        },
        {
          "Category": "Data",
          "PropertyName": "LinealGradientColour2",
          "RuleProviderType": "Unknown"
        },
        {
          "Category": "Data",
          "PropertyName": "borderradius",
          "RuleProviderType": "System"
        },
        {
          "Category": "Data",
          "PropertyName": "DarkMode",
          "RuleProviderType": "Unknown"
        },
        {
          "Category": "Design",
          "PropertyName": "ZIndex",
          "RuleProviderType": "Unknown"
        },
        {
          "Category": "Design",
          "PropertyName": "Fill",
          "RuleProviderType": "System"
        },
        {
          "Category": "Design",
          "PropertyName": "Height",
          "RuleProviderType": "Unknown"
        },
        {
          "Category": "Design",
          "PropertyName": "Y",
          "RuleProviderType": "Unknown"
        },
        {
          "Category": "Design",
          "PropertyName": "X",
          "RuleProviderType": "Unknown"
        },
        {
          "Category": "Design",
          "PropertyName": "Width",
          "RuleProviderType": "Unknown"
        }
      ],
      "StyleName": "",
      "Type": "ControlInfo"
    },
    "Slider_6": {
      "AllowAccessToGlobals": true,
      "ControlPropertyState": [
        {
          "AFDDataSourceName": "",
          "AutoRuleBindingEnabled": false,
          "AutoRuleBindingString": "",
          "InvariantPropertyName": "Fill",
          "IsLockable": false,
          "NameMapSourceSchema": "?"
        },
        {
          "AFDDataSourceName": "",
          "AutoRuleBindingEnabled": false,
          "AutoRuleBindingString": "",
          "InvariantPropertyName": "Height",
          "IsLockable": false,
          "NameMapSourceSchema": "?"
        },
        {
          "AFDDataSourceName": "",
          "AutoRuleBindingEnabled": false,
          "AutoRuleBindingString": "",
          "InvariantPropertyName": "Width",
          "IsLockable": false,
          "NameMapSourceSchema": "?"
        },
        "X",
        "Y",
        "ZIndex",
        {
          "AFDDataSourceName": "",
          "AutoRuleBindingEnabled": false,
          "AutoRuleBindingString": "100",
          "InvariantPropertyName": "Value",
          "IsLockable": false,
          "NameMapSourceSchema": "?"
        },
        "Max",
        "Min",
        {
          "AFDDataSourceName": "",
          "AutoRuleBindingEnabled": false,
          "AutoRuleBindingString": "\"#2c3e50\"",
          "InvariantPropertyName": "LinealGradientColour1",
          "IsLockable": false,
          "NameMapSourceSchema": "?"
        },
        {
          "AFDDataSourceName": "",
          "AutoRuleBindingEnabled": false,
          "AutoRuleBindingString": "\"#3498db\"",
          "InvariantPropertyName": "LinealGradientColour2",
          "IsLockable": false,
          "NameMapSourceSchema": "?"
        },
        "borderradius",
        {
          "AFDDataSourceName": "",
          "AutoRuleBindingEnabled": false,
          "AutoRuleBindingString": "true",
          "InvariantPropertyName": "DarkMode",
          "IsLockable": false,
          "NameMapSourceSchema": "?"
        }
      ],
      "HasDynamicProperties": false,
      "IsAutoGenerated": false,
      "IsComponentDefinition": false,
      "IsDataControl": false,
      "IsFromScreenLayout": false,
      "IsGroupControl": false,
      "IsLocked": false,
      "LayoutName": "",
      "Metadata": {
        "AllowAccessToGlobals": false,
        "AllowCustomization": true,
        "Description": "スライダー"
      },
      "MetaDataIDKey": "",
      "Name": "Slider_6",
      "ParentIndex": 7,
      "PersistMetaDataIDKey": false,
      "Properties": [
        {
          "Category": "Data",
          "PropertyName": "Min",
          "RuleProviderType": "System"
        },
        {
          "Category": "Data",
          "PropertyName": "Max",
          "RuleProviderType": "System"
        },
        {
          "Category": "Data",
          "PropertyName": "Value",
          "RuleProviderType": "System"
        },
        {
          "Category": "Data",
          "PropertyName": "LinealGradientColour1",
          "RuleProviderType": "Unknown"
        },
        {
          "Category": "Data",
          "PropertyName": "LinealGradientColour2",
          "RuleProviderType": "Unknown"
        },
        {
          "Category": "Data",
          "PropertyName": "borderradius",
          "RuleProviderType": "System"
        },
        {
          "Category": "Data",
          "PropertyName": "DarkMode",
          "RuleProviderType": "Unknown"
        },
        {
          "Category": "Design",
          "PropertyName": "ZIndex",
          "RuleProviderType": "Unknown"
        },
        {
          "Category": "Design",
          "PropertyName": "Fill",
          "RuleProviderType": "System"
        },
        {
          "Category": "Design",
          "PropertyName": "Height",
          "RuleProviderType": "Unknown"
        },
        {
          "Category": "Design",
          "PropertyName": "Y",
          "RuleProviderType": "Unknown"
        },
        {
          "Category": "Design",
          "PropertyName": "X",
          "RuleProviderType": "Unknown"
        },
        {
          "Category": "Design",
          "PropertyName": "Width",
          "RuleProviderType": "Unknown"
        }
      ],
      "StyleName": "",
      "Type": "ControlInfo"
    },
    "Toggle_1": {
      "AllowAccessToGlobals": true,
      "ControlPropertyState": [
        "Fill",
        {
          "AFDDataSourceName": "",
          "AutoRuleBindingEnabled": false,
          "AutoRuleBindingString": "",
          "InvariantPropertyName": "Height",
          "IsLockable": false,
          "NameMapSourceSchema": "?"
        },
        {
          "AFDDataSourceName": "",
          "AutoRuleBindingEnabled": false,
          "AutoRuleBindingString": "",
          "InvariantPropertyName": "Width",
          "IsLockable": false,
          "NameMapSourceSchema": "?"
        },
        "X",
        "Y",
        "ZIndex",
        "Toggled",
        {
          "AFDDataSourceName": "",
          "AutoRuleBindingEnabled": false,
          "AutoRuleBindingString": "\"#2c3e50\"",
          "InvariantPropertyName": "LinealGradientColour1",
          "IsLockable": false,
          "NameMapSourceSchema": "?"
        },
        {
          "AFDDataSourceName": "",
          "AutoRuleBindingEnabled": false,
          "AutoRuleBindingString": "\"#2398db\"",
          "InvariantPropertyName": "LinealGradientColour2",
          "IsLockable": false,
          "NameMapSourceSchema": "?"
        },
        "IconVisible",
        {
          "AFDDataSourceName": "",
          "AutoRuleBindingEnabled": false,
          "AutoRuleBindingString": "true",
          "InvariantPropertyName": "DarkMode",
          "IsLockable": false,
          "NameMapSourceSchema": "?"
        },
        {
          "AFDDataSourceName": "",
          "AutoRuleBindingEnabled": false,
          "AutoRuleBindingString": "",
          "InvariantPropertyName": "borderRadius",
          "IsLockable": false,
          "NameMapSourceSchema": "?"
        }
      ],
      "HasDynamicProperties": false,
      "IsAutoGenerated": false,
      "IsComponentDefinition": false,
      "IsDataControl": false,
      "IsFromScreenLayout": false,
      "IsGroupControl": false,
      "IsLocked": false,
      "LayoutName": "",
      "Metadata": {
        "AllowAccessToGlobals": false,
        "AllowCustomization": true,
        "Description": "トグル"
      },
      "MetaDataIDKey": "",
      "Name": "Toggle_1",
      "ParentIndex": 5,
      "PersistMetaDataIDKey": false,
      "Properties": [
        {
          "Category": "Data",
          "PropertyName": "IconVisible",
          "RuleProviderType": "System"
        },
        {
          "Category": "Data",
          "PropertyName": "LinealGradientColour2",
          "RuleProviderType": "Unknown"
        },
        {
          "Category": "Data",
          "PropertyName": "LinealGradientColour1",
          "RuleProviderType": "Unknown"
        },
        {
          "Category": "Data",
          "PropertyName": "Toggled",
          "RuleProviderType": "System"
        },
        {
          "Category": "Data",
          "PropertyName": "DarkMode",
          "RuleProviderType": "Unknown"
        },
        {
          "Category": "Data",
          "PropertyName": "borderRadius",
          "RuleProviderType": "Unknown"
        },
        {
          "Category": "Design",
          "PropertyName": "X",
          "RuleProviderType": "Unknown"
        },
        {
          "Category": "Design",
          "PropertyName": "Fill",
          "RuleProviderType": "System"
        },
        {
          "Category": "Design",
          "PropertyName": "Y",
          "RuleProviderType": "Unknown"
        },
        {
          "Category": "Design",
          "PropertyName": "ZIndex",
          "RuleProviderType": "Unknown"
        },
        {
          "Category": "Design",
          "PropertyName": "Width",
          "RuleProviderType": "Unknown"
        },
        {
          "Category": "Design",
          "PropertyName": "Height",
          "RuleProviderType": "Unknown"
        }
      ],
      "StyleName": "",
      "Type": "ControlInfo"
    },
    "TOP": {
      "AllowAccessToGlobals": true,
      "ControlPropertyState": [
        {
          "AFDDataSourceName": "",
          "AutoRuleBindingEnabled": false,
          "AutoRuleBindingString": "",
          "InvariantPropertyName": "Fill",
          "IsLockable": false,
          "NameMapSourceSchema": "?"
        },
        "ImagePosition",
        "Height",
        "Width",
        "Size",
        "Orientation",
        "LoadingSpinner",
        "LoadingSpinnerColor"
      ],
      "IsAutoGenerated": false,
      "IsComponentDefinition": false,
      "IsDataControl": false,
      "IsFromScreenLayout": false,
      "IsGroupControl": false,
      "IsLocked": false,
      "LayoutName": "",
      "MetaDataIDKey": "",
      "Name": "TOP",
      "ParentIndex": 0,
      "PersistMetaDataIDKey": false,
      "Properties": [
        {
          "Category": "Design",
          "PropertyName": "Fill",
          "RuleProviderType": "Unknown"
        },
        {
          "Category": "Design",
          "PropertyName": "ImagePosition",
          "RuleProviderType": "Unknown"
        },
        {
          "Category": "Design",
          "PropertyName": "Height",
          "RuleProviderType": "Unknown"
        },
        {
          "Category": "Design",
          "PropertyName": "Width",
          "RuleProviderType": "Unknown"
        },
        {
          "Category": "Design",
          "PropertyName": "Size",
          "RuleProviderType": "Unknown"
        },
        {
          "Category": "Design",
          "PropertyName": "Orientation",
          "RuleProviderType": "Unknown"
        },
        {
          "Category": "Design",
          "PropertyName": "LoadingSpinner",
          "RuleProviderType": "Unknown"
        },
        {
          "Category": "Design",
          "PropertyName": "LoadingSpinnerColor",
          "RuleProviderType": "Unknown"
        }
      ],
      "StyleName": "defaultScreenStyle",
      "Type": "ControlInfo"
    }
  },
  "TopParentName": "TOP"
}